immunio/__init__.py
immunio/_version.py
immunio/agent.py
immunio/compat.py
immunio/config.py
immunio/context.py
immunio/counters.py
immunio/exceptions.py
immunio/immunio_ca.crt
immunio/import_monitor.py
immunio/libagent.py
immunio/logger.py
immunio/patcher.py
immunio/plugin_manager.py
immunio/singleton.py
immunio/start.py
immunio/util.py
immunio/wsgi.py
immunio/api/__init__.py
immunio/api/auth.py
immunio/api/extend.py
immunio/deps/__init__.py
immunio/deps/cachetools/__init__.py
immunio/deps/cachetools/abc.py
immunio/deps/cachetools/backport_collections.py
immunio/deps/cachetools/cache.py
immunio/deps/cachetools/func.py
immunio/deps/cachetools/keys.py
immunio/deps/cachetools/lfu.py
immunio/deps/cachetools/lru.py
immunio/deps/cachetools/rr.py
immunio/deps/cachetools/ttl.py
immunio/deps/libagent/agent.h
immunio/deps/libagent/libagent-x86_64-Darwin.dylib
immunio/deps/portalocker/__about__.py
immunio/deps/portalocker/__init__.py
immunio/deps/portalocker/constants.py
immunio/deps/portalocker/exceptions.py
immunio/deps/portalocker/portalocker.py
immunio/deps/portalocker/utils.py
immunio/deps/python_ifcfg/__init__.py
immunio/deps/python_ifcfg/setup.py
immunio/deps/python_ifcfg/ifcfg/__init__.py
immunio/deps/python_ifcfg/ifcfg/exc.py
immunio/deps/python_ifcfg/ifcfg/meta.py
immunio/deps/python_ifcfg/ifcfg/parser.py
immunio/deps/python_ifcfg/ifcfg/tools.py
immunio/deps/python_ifcfg/tests/__init__.py
immunio/deps/python_ifcfg/tests/exc_tests.py
immunio/deps/python_ifcfg/tests/ifcfg_tests.py
immunio/deps/python_ifcfg/tests/ifconfig_out.py
immunio/deps/python_ifcfg/tests/meta_tests.py
immunio/deps/python_ifcfg/tests/tools_tests.py
immunio/plugins/__init__.py
immunio/plugins/dbapi2_helper.py
immunio/plugins/plugin_django.py
immunio/plugins/plugin_django_xss.py
immunio/plugins/plugin_fileio.py
immunio/plugins/plugin_flask.py
immunio/plugins/plugin_jinja2.py
immunio/plugins/plugin_mysqldb.py
immunio-2.3.3.dist-info/DESCRIPTION.rst
immunio-2.3.3.dist-info/METADATA
immunio-2.3.3.dist-info/RECORD
immunio-2.3.3.dist-info/WHEEL
immunio-2.3.3.dist-info/metadata.json
immunio-2.3.3.dist-info/top_level.txt
