Metadata-Version: 2.0
Name: immunio
Version: 2.3.3
Summary: Immunio agent library
Home-page: https://www.immun.io
Author: Immunio
Author-email: contact@immun.io
License: UNKNOWN
Platform: UNKNOWN
Classifier: Framework :: Django
Classifier: Framework :: Flask
Classifier: Framework :: Pyramid
Classifier: Intended Audience :: Developers
Classifier: License :: Other/Proprietary License
Classifier: Programming Language :: Python :: 2.7
Classifier: Programming Language :: Python :: 3.3
Classifier: Programming Language :: Python :: 3.4
Classifier: Programming Language :: Python :: 3.5
Classifier: Programming Language :: Python :: 3.6
Classifier: Programming Language :: Python :: 3.7
Classifier: Topic :: Security
Requires-Dist: cffi
